LICENSE
MANIFEST.in
README.md
ez_setup.py
setup.py
nebgbdiff/__init__.py
nebgbdiff/location.py
nebgbdiff/main.py
nebgbdiff/merge.py
nebgbdiff/meta.py
nebgbdiff/sequence.py
nebgbdiff.egg-info/PKG-INFO
nebgbdiff.egg-info/SOURCES.txt
nebgbdiff.egg-info/dependency_links.txt
nebgbdiff.egg-info/entry_points.txt
nebgbdiff.egg-info/not-zip-safe
nebgbdiff.egg-info/requires.txt
nebgbdiff.egg-info/top_level.txt